LICENSE
README.md
setup.py
lib/shotgun/__init__.py
lib/shotgun/asset.py
lib/shotgun/base.py
lib/shotgun/config.py
lib/shotgun/dotdictify.py
lib/shotgun/logger.py
lib/shotgun/media.py
lib/shotgun/person.py
lib/shotgun/playlist.py
lib/shotgun/project.py
lib/shotgun/sequence.py
lib/shotgun/shot.py
lib/shotgun/shotgun.py
lib/shotgun/task.py
lib/shotgun/version.py
lib/shotgunwrapper.egg-info/PKG-INFO
lib/shotgunwrapper.egg-info/SOURCES.txt
lib/shotgunwrapper.egg-info/dependency_links.txt
lib/shotgunwrapper.egg-info/not-zip-safe
lib/shotgunwrapper.egg-info/top_level.txt
tests/test.py