Metadata-Version: 2.1
Name: shotgunwrapper
Version: 0.1.0
Summary: Pythonic Shotgun API wrapper
Home-page: http://github.com/rsgalloway/shotgunwrapper
Author: Ryan Galloway
Author-email: ryan@rsgalloway.com
Requires-Python: >=3.8
License-File: LICENSE
